CHANGELOG.txt
LICENSE.txt
MANIFEST.in
README.txt
ez_setup.py
setup.cfg
setup.py
ConversionKit.egg-info/PKG-INFO
ConversionKit.egg-info/SOURCES.txt
ConversionKit.egg-info/dependency_links.txt
ConversionKit.egg-info/entry_points.txt
ConversionKit.egg-info/not-zip-safe
ConversionKit.egg-info/requires.txt
ConversionKit.egg-info/top_level.txt
conversionkit/__init__.py
conversionkit/exception.py
conversionkit/types.py
doc/Makefile
doc/index.txt
doc/source/api.rst
doc/source/conf.py
doc/source/formencode.rst
doc/source/i18n.rst
doc/source/index.rst
doc/source/manual.rst
test/doc.py
test/formencode_doc.py