Metadata-Version: 1.0
Name: ConversionKit
Version: 0.3.4
Summary: A general purpose conversion library
Home-page: http://jimmyg.org/work/code/conversionkit/index.html
Author: James Gardner
Author-email: UNKNOWN
License: GNU AGPLv3
Platform: UNKNOWN
Classifier: Development Status :: 3 - Alpha
Classifier: License :: OSI Approved :: GNU Affero General Public License v3
Classifier: Programming Language :: Python :: 2
Classifier: Topic :: Software Development :: Libraries :: Python Modules
Classifier: Environment :: Web Environment
Classifier: Environment :: Console
